yaqd_rpi_gpio/VERSION
yaqd_rpi_gpio/__init__.py
yaqd_rpi_gpio/__version__.py
yaqd_rpi_gpio/_gpio_digital_output.py
yaqd_rpi_gpio/_gpio_digital_sensor.py
yaqd_rpi_gpio/gpio-digital-output.avpr
yaqd_rpi_gpio/gpio-digital-output.toml
yaqd_rpi_gpio/gpio-digital-sensor.avpr
yaqd_rpi_gpio/gpio-digital-sensor.toml
yaqd_rpi_gpio-2024.2.0.dist-info/entry_points.txt
yaqd_rpi_gpio-2024.2.0.dist-info/LICENSE
yaqd_rpi_gpio-2024.2.0.dist-info/WHEEL
yaqd_rpi_gpio-2024.2.0.dist-info/METADATA
yaqd_rpi_gpio-2024.2.0.dist-info/RECORD
