Metadata-Version: 2.1
Name: yaqd-rpi-gpio
Version: 2024.2.0
Summary: yaq daemons for control of Rasperry Pi GPIO
Home-page: https://yaq.fyi
Author: Blaise Thompson
Author-email: blaise@untzag.com
Requires-Python: >=3.7
Classifier: Development Status :: 4 - Beta
Classifier: Intended Audience :: Science/Research
Classifier: License :: OSI Approved :: GNU Lesser General Public License v3 (LGPLv3)
Classifier: Natural Language :: English
Classifier: Programming Language :: Python :: 3
Classifier: Programming Language :: Python :: 3.7
Classifier: Programming Language :: Python :: 3.8
Classifier: Topic :: Scientific/Engineering
Requires-Dist: yaqd-core>=2021.3.0
Requires-Dist: gpiozero
Requires-Dist: black ; extra == "dev"
Requires-Dist: pre-commit ; extra == "dev"
Project-URL: Issues, https://gitlab.com/yaq/yaqd-rpi-gpio/-/issues
Project-URL: Source, https://gitlab.com/yaq/yaqd-rpi-gpio
Provides-Extra: dev
